datasette_marimo/__init__.py
datasette_marimo/static/.nojekyll
datasette_marimo/static/android-chrome-192x192.png
datasette_marimo/static/android-chrome-512x512.png
datasette_marimo/static/apple-touch-icon.png
datasette_marimo/static/circle-check.ico
datasette_marimo/static/circle-play.ico
datasette_marimo/static/circle-x.ico
datasette_marimo/static/favicon-16x16.png
datasette_marimo/static/favicon-32x32.png
datasette_marimo/static/favicon.ico
datasette_marimo/static/index.html
datasette_marimo/static/logo.png
datasette_marimo/static/manifest.json
datasette_marimo/static/site.webmanifest
datasette_marimo/static/assets/ConnectedDataExplorerComponent-B-AZoBol.js
datasette_marimo/static/assets/ConnectedDataExplorerComponent-xxNEGG9e.js
datasette_marimo/static/assets/FiraMono-Bold-CLVRCuM9.ttf
datasette_marimo/static/assets/FiraMono-Medium-DU3aDxX5.ttf
datasette_marimo/static/assets/FiraMono-Regular-BTCkDNvf.ttf
datasette_marimo/static/assets/KaTeX_AMS-Regular-BQhdFMY1.woff2
datasette_marimo/static/assets/KaTeX_AMS-Regular-DMm9YOAa.woff
datasette_marimo/static/assets/KaTeX_AMS-Regular-DRggAlZN.ttf
datasette_marimo/static/assets/KaTeX_Caligraphic-Bold-ATXxdsX0.ttf
datasette_marimo/static/assets/KaTeX_Caligraphic-Bold-BEiXGLvX.woff
datasette_marimo/static/assets/KaTeX_Caligraphic-Bold-Dq_IR9rO.woff2
datasette_marimo/static/assets/KaTeX_Caligraphic-Regular-CTRA-rTL.woff
datasette_marimo/static/assets/KaTeX_Caligraphic-Regular-Di6jR-x-.woff2
datasette_marimo/static/assets/KaTeX_Caligraphic-Regular-wX97UBjC.ttf
datasette_marimo/static/assets/KaTeX_Fraktur-Bold-BdnERNNW.ttf
datasette_marimo/static/assets/KaTeX_Fraktur-Bold-BsDP51OF.woff
datasette_marimo/static/assets/KaTeX_Fraktur-Bold-CL6g_b3V.woff2
datasette_marimo/static/assets/KaTeX_Fraktur-Regular-CB_wures.ttf
datasette_marimo/static/assets/KaTeX_Fraktur-Regular-CTYiF6lA.woff2
datasette_marimo/static/assets/KaTeX_Fraktur-Regular-Dxdc4cR9.woff
datasette_marimo/static/assets/KaTeX_Main-Bold-Cx986IdX.woff2
datasette_marimo-0.1.4.dist-info/METADATA
datasette_marimo-0.1.4.dist-info/WHEEL
datasette_marimo-0.1.4.dist-info/entry_points.txt
datasette_marimo-0.1.4.dist-info/licenses/LICENSE
datasette_marimo-0.1.4.dist-info/RECORD
