Metadata-Version: 2.4
Name: datasette-marimo
Version: 0.1.4
Summary: Marimo attached to your datasette
Project-URL: Homepage, https://github.com/koaning/datasette-marimo
Project-URL: Changelog, https://github.com/koaning/datasette-marimo/releases
Project-URL: Issues, https://github.com/koaning/datasette-marimo/issues
Project-URL: CI, https://github.com/koaning/datasette-marimo/actions
Author: Vincent D. Warmerdam
License: Apache-2.0
License-File: LICENSE
Classifier: Framework :: Datasette
Classifier: License :: OSI Approved :: Apache Software License
Requires-Python: >=3.9
Requires-Dist: datasette>=1.0a16
Requires-Dist: marimo
Requires-Dist: polars
Requires-Dist: requests
Requires-Dist: yarl
Provides-Extra: test
Requires-Dist: pytest; extra == 'test'
Requires-Dist: pytest-asyncio; extra == 'test'
